osso_docktool/__init__.py
osso_docktool/__main__.py
osso_docktool/devtype.py
osso_docktool/disksampler.py
osso_docktool/docktool.py
osso_docktool/hdddock.py
osso_docktool/hdparm.py
osso_docktool/inventoryrestclient.py
osso_docktool/jwt_token_provider.py
osso_docktool/labelprinterapiclient.py
osso_docktool/nvmedata.py
osso_docktool/settings.py
osso_docktool/smartdata.py
osso_docktool-1.9.8.data/data/share/doc/osso-docktool/README.rst
osso_docktool-1.9.8.data/data/share/doc/osso-docktool/local_settings.py.template
osso_docktool-1.9.8.dist-info/METADATA
osso_docktool-1.9.8.dist-info/WHEEL
osso_docktool-1.9.8.dist-info/entry_points.txt
osso_docktool-1.9.8.dist-info/top_level.txt
osso_docktool-1.9.8.dist-info/RECORD
