Metadata-Version: 2.4
Name: osso-docktool
Version: 1.9.8
Summary: HDD administration and maintenance
Home-page: https://git.osso.nl/osso-io/docktool
Author: OSSO B.V.
Author-email: dev+osso-docktool@osso.nl
License: Undecided
Classifier: Development Status :: 4 - Beta
Classifier: Intended Audience :: Developers
Classifier: Intended Audience :: End Users/Desktop
Classifier: Intended Audience :: System Administrators
Classifier: Programming Language :: Python :: 3
Classifier: Programming Language :: Python :: 3.5
Classifier: Programming Language :: Python :: 3.6
Classifier: Programming Language :: Python :: 3.7
Classifier: Programming Language :: Python :: 3.8
Classifier: Topic :: System :: Filesystems
Classifier: Topic :: Utilities
Requires-Dist: requests
Dynamic: author
Dynamic: author-email
Dynamic: classifier
Dynamic: description
Dynamic: home-page
Dynamic: license
Dynamic: requires-dist
Dynamic: summary
